interactive_multi_category_table/__init__.py
interactive_multi_category_table/template.html
interactive_multi_category_table/to_dash.py
interactive_multi_category_table/to_html.py
interactive_multi_category_table/utils.py
interactive_multi_category_table-0.0.4.dist-info/METADATA
interactive_multi_category_table-0.0.4.dist-info/WHEEL
interactive_multi_category_table-0.0.4.dist-info/licenses/LICENSE
interactive_multi_category_table-0.0.4.dist-info/RECORD
