Metadata-Version: 2.1
Name: interactive_multi_category_table
Version: 0.0.4
Summary: A python package to create interactive tables with alternative category views from formatted json input.
Project-URL: Homepage, https://github.com/XiangCHEN-dvi/interactive-multi-category-table
Project-URL: Bug Tracker, https://github.com/XiangCHEN-dvi/interactive-multi-category-table/issues
Author-email: Xiang CHEN <xiangchen.ai@outlook.com>
License-File: LICENSE
Classifier: License :: OSI Approved :: Apache Software License
Classifier: Operating System :: OS Independent
Classifier: Programming Language :: Python :: 3
Requires-Python: >=3.7
